{
  "version": 1,
  "updated_at": "2025-10-25T17:33:15.615249+00:00",
  "feeds": {
    "commentisfree": {
      "feed_url": null,
      "recent_url_hashes": [],
      "recent_url_hashes_max": 1000
    },
    "theguardian": {
      "feed_url": null,
      "recent_url_hashes": [],
      "recent_url_hashes_max": 500
    },
    "vox": {
      "feed_url": "https://www.vox.com/rss/index.xml",
      "recent_url_hashes": [],
      "recent_url_hashes_max": 1000,
      "last_run_at": "2025-10-25T17:33:03.788989+00:00"
    },
    "cnn-opinion": {
      "feed_url": "http://rss.cnn.com/rss/cnn_opinion.rss",
      "recent_url_hashes": [],
      "recent_url_hashes_max": 1000,
      "last_run_at": null
    },
    "guardian": {
      "feed_url": "https://www.theguardian.com/uk/rss",
      "recent_url_hashes": [],
      "recent_url_hashes_max": 1000,
      "last_run_at": "2025-10-25T17:33:04.830946+00:00"
    },
    "bbc": {
      "feed_url": "https://feeds.bbci.co.uk/news/rss.xml",
      "recent_url_hashes": [],
      "recent_url_hashes_max": 1000,
      "last_run_at": "2025-10-25T17:33:04.995681+00:00"
    },
    "cityjournal": {
      "feed_url": "https://www.city-journal.org/rss.xml",
      "recent_url_hashes": [],
      "recent_url_hashes_max": 1000,
      "last_run_at": "2025-10-25T17:33:05.131797+00:00"
    },
    "dailycaller": {
      "feed_url": "https://dailycaller.com/feed/",
      "recent_url_hashes": [],
      "recent_url_hashes_max": 1000,
      "last_run_at": "2025-10-25T17:33:06.821441+00:00"
    },
    "theconversation": {
      "feed_url": "https://theconversation.com/us/articles.atom",
      "recent_url_hashes": [],
      "recent_url_hashes_max": 1000,
      "last_run_at": "2025-10-25T17:33:08.047459+00:00"
    },
    "aljazeera": {
      "feed_url": "https://www.aljazeera.com/xml/rss/all.xml",
      "recent_url_hashes": [],
      "recent_url_hashes_max": 1000,
      "last_run_at": "2025-10-25T17:33:08.190404+00:00"
    },
    "foxnews": {
      "feed_url": "https://moxie.foxnews.com/google-publisher/latest.xml",
      "recent_url_hashes": [],
      "recent_url_hashes_max": 1000,
      "last_run_at": "2025-10-25T17:33:08.598356+00:00"
    },
    "npr": {
      "feed_url": "https://feeds.npr.org/1001/rss.xml",
      "recent_url_hashes": [],
      "recent_url_hashes_max": 1000,
      "last_run_at": "2025-10-25T17:33:09.468292+00:00"
    },
    "reason": {
      "feed_url": "https://reason.com/feed/",
      "recent_url_hashes": [],
      "recent_url_hashes_max": 1000,
      "last_run_at": "2025-10-25T17:33:11.167089+00:00"
    },
    "thefederalist": {
      "feed_url": "https://thefederalist.com/feed/",
      "recent_url_hashes": [],
      "recent_url_hashes_max": 1000,
      "last_run_at": "2025-10-25T17:33:12.551857+00:00"
    },
    "msnbc": {
      "feed_url": "https://feeds.nbcnews.com/msnbc/public/news",
      "recent_url_hashes": [],
      "recent_url_hashes_max": 1000,
      "last_run_at": "2025-10-25T17:33:13.567038+00:00"
    },
    "nypost": {
      "feed_url": "https://nypost.com/feed/",
      "recent_url_hashes": [],
      "recent_url_hashes_max": 1000,
      "last_run_at": "2025-10-25T17:33:15.615030+00:00"
    }
  }
}